ssam-1.1.2.dist-info/top_level.txt
ssam-1.1.2.dist-info/LICENSE.agpl
ssam-1.1.2.dist-info/RECORD
ssam-1.1.2.dist-info/LICENSE
ssam-1.1.2.dist-info/METADATA
ssam-1.1.2.dist-info/WHEEL
ssam/_dataset.py
ssam/_analysis.py
ssam/__init__.py
ssam/utils.cpython-39-x86_64-linux-gnu.so
ssam/aaec/_loss_functions.py
ssam/aaec/_train_utils.py
ssam/aaec/_model.py
ssam/aaec/__init__.py
ssam/aaec/_train_semi_supervised_ssam.py
ssam/aaec/_train_unsupervised_ssam.py
ssam.libs/libgomp-a34b3233.so.1.0.0
