Metadata-Version: 2.1
Name: ssam
Version: 1.1.2
Summary: SSAM
Home-page: https://github.com/pnucolab/ssam
Author: Jeongbin Park
Author-email: jeongbin.park@pusan.ac.kr
Classifier: Programming Language :: Python :: 3
Classifier: License :: OSI Approved :: GNU Affero General Public License v3 or later (AGPLv3+)
Classifier: Operating System :: POSIX
License-File: LICENSE
License-File: LICENSE.agpl
Requires-Dist: numpy <=2.0.2,>=1.26.4
Requires-Dist: zarr <3
Requires-Dist: networkx
Requires-Dist: numba
Requires-Dist: scipy
Requires-Dist: pandas
Requires-Dist: matplotlib
Requires-Dist: seaborn
Requires-Dist: scikit-learn
Requires-Dist: umap-learn
Requires-Dist: leidenalg
Requires-Dist: sparse
Requires-Dist: scikit-image
Requires-Dist: dask
Requires-Dist: dask[array]
Requires-Dist: opencv-python
Requires-Dist: packaging
Requires-Dist: tqdm
